odoo/addons/contract_variable_qty_timesheet/README.rst
odoo/addons/contract_variable_qty_timesheet/__init__.py
odoo/addons/contract_variable_qty_timesheet/__manifest__.py
odoo/addons/contract_variable_qty_timesheet/data/contract_line_qty_formula_data.xml
odoo/addons/contract_variable_qty_timesheet/i18n/contract_variable_qty_timesheet.pot
odoo/addons/contract_variable_qty_timesheet/i18n/de.po
odoo/addons/contract_variable_qty_timesheet/i18n/es.po
odoo/addons/contract_variable_qty_timesheet/i18n/fr.po
odoo/addons/contract_variable_qty_timesheet/i18n/it.po
odoo/addons/contract_variable_qty_timesheet/i18n/pt.po
odoo/addons/contract_variable_qty_timesheet/i18n/pt_BR.po
odoo/addons/contract_variable_qty_timesheet/i18n/zh.po
odoo/addons/contract_variable_qty_timesheet/readme/CONTRIBUTORS.md
odoo/addons/contract_variable_qty_timesheet/readme/DESCRIPTION.md
odoo/addons/contract_variable_qty_timesheet/readme/USAGE.md
odoo/addons/contract_variable_qty_timesheet/setup/.setuptools-odoo-make-default-ignore
odoo/addons/contract_variable_qty_timesheet/setup/README
odoo/addons/contract_variable_qty_timesheet/static/description/icon.png
odoo/addons/contract_variable_qty_timesheet/static/description/index.html
odoo/addons/contract_variable_qty_timesheet/tests/__init__.py
odoo/addons/contract_variable_qty_timesheet/tests/test_contract_variable_qty_timesheet.py
odoo_addon_contract_variable_qty_timesheet-17.0.1.0.0.3.dist-info/METADATA
odoo_addon_contract_variable_qty_timesheet-17.0.1.0.0.3.dist-info/WHEEL
odoo_addon_contract_variable_qty_timesheet-17.0.1.0.0.3.dist-info/top_level.txt
odoo_addon_contract_variable_qty_timesheet-17.0.1.0.0.3.dist-info/RECORD
