Metadata-Version: 2.1
Name: odoo-addon-contract_variable_qty_timesheet
Version: 17.0.1.0.0.3
Requires-Python: >=3.10
Requires-Dist: odoo-addon-contract_variable_quantity>=17.0dev,<17.1dev
Requires-Dist: odoo>=17.0a,<17.1dev
Summary: Add formula to invoice
Home-page: https://github.com/OCA/contract
License: AGPL-3
Author: Tecnativa, Odoo Community Association (OCA)
Author-email: support@odoo-community.org
Classifier: Programming Language :: Python
Classifier: Framework :: Odoo
Classifier: Framework :: Odoo :: 17.0
Classifier: License :: OSI Approved :: GNU Affero General Public License v3
